{"basic": [{"notation": "C", "array": [1, 0, 0, 0, 1, 0, 0, 1, 0, 0, 0, 0], "root": "C", "quality": "M", "bass": "C"}, {"notation": "Cm", "array": [1, 0, 0, 1, 0, 0, 0, 1, 0, 0, 0, 0], "root": "C", "quality": "m", "bass": "C"}, {"notation": "Caug", "array": [1, 0, 0, 0, 1, 0, 0, 0, 1, 0, 0, 0], "root": "C", "quality": "aug", "bass": "C"}, {"notation": "Cdim", "array": [1, 0, 0, 1, 0, 0, 1, 0, 0, 0, 0, 0], "root": "C", "quality": "dim", "bass": "C"}, {"notation": "C7", "array": [1, 0, 0, 0, 1, 0, 0, 1, 0, 0, 1, 0], "root": "C", "quality": "7", "bass": "C"}, {"notation": "Cm7", "array": [1, 0, 0, 1, 0, 0, 0, 1, 0, 0, 1, 0], "root": "C", "quality": "m7", "bass": "C"}, {"notation": "Cmaj7", "array": [1, 0, 0, 0, 1, 0, 0, 1, 0, 0, 0, 1], "root": "C", "quality": "maj7", "bass": "C"}, {"notation": "Cdim7", "array": [1, 0, 0, 1, 0, 0, 1, 0, 0, 1, 0, 0], "root": "C", "quality": "dim7", "bass": "C"}, {"notation": "C\u00f87", "array": [1, 0, 0, 1, 0, 0, 1, 0, 0, 0, 1, 0], "root": "C", "quality": "\u00f87", "bass": "C"}, {"notation": "C9", "array": [1, 0, 1, 0, 1, 0, 0, 1, 0, 0, 1, 0], "root": "C", "quality": "9", "bass": "C"}, {"notation": "Cadd9", "array": [1, 0, 1, 0, 1, 0, 0, 1, 0, 0, 0, 0], "root": "C", "quality": "add9", "bass": "C"}, {"notation": "Cadd6", "array": [1, 0, 0, 0, 1, 0, 0, 1, 0, 1, 0, 0], "root": "C", "quality": "add6", "bass": "C"}, {"notation": "Csus2", "array": [1, 0, 1, 0, 0, 0, 0, 1, 0, 0, 0, 0], "root": "C", "quality": "sus2", "bass": "C"}, {"notation": "Csus4", "array": [1, 0, 0, 0, 0, 1, 0, 1, 0, 0, 0, 0], "root": "C", "quality": "sus4", "bass": "C"}, {"notation": "C#", "array": [0, 1, 0, 0, 0, 1, 0, 0, 1, 0, 0, 0], "root": "C#", "quality": "M", "bass": "C#"}, {"notation": "C#m", "array": [0, 1, 0, 0, 1, 0, 0, 0, 1, 0, 0, 0], "root": "C#", "quality": "m", "bass": "C#"}, {"notation": "C#aug", "array": [0, 1, 0, 0, 0, 1, 0, 0, 0, 1, 0, 0], "root": "C#", "quality": "aug", "bass": "C#"}, {"notation": "C#dim", "array": [0, 1, 0, 0, 1, 0, 0, 1, 0, 0, 0, 0], "root": "C#", "quality": "dim", "bass": "C#"}, {"notation": "C#7", "array": [0, 1, 0, 0, 0, 1, 0, 0, 1, 0, 0, 1], "root": "C#", "quality": "7", "bass": "C#"}, {"notation": "C#m7", "array": [0, 1, 0, 0, 1, 0, 0, 0, 1, 0, 0, 1], "root": "C#", "quality": "m7", "bass": "C#"}, {"notation": "C#maj7", "array": [1, 1, 0, 0, 0, 1, 0, 0, 1, 0, 0, 0], "root": "C#", "quality": "maj7", "bass": "C#"}, {"notation": "C#dim7", "array": [0, 1, 0, 0, 1, 0, 0, 1, 0, 0, 1, 0], "root": "C#", "quality": "dim7", "bass": "C#"}, {"notation": "C#\u00f87", "array": [0, 1, 0, 0, 1, 0, 0, 1, 0, 0, 0, 1], "root": "C#", "quality": "\u00f87", "bass": "C#"}, {"notation": "C#9", "array": [0, 1, 0, 1, 0, 1, 0, 0, 1, 0, 0, 1], "root": "C#", "quality": "9", "bass": "C#"}, {"notation": "C#add9", "array": [0, 1, 0, 1, 0, 1, 0, 0, 1, 0, 0, 0], "root": "C#", "quality": "add9", "bass": "C#"}, {"notation": "C#add6", "array": [0, 1, 0, 0, 0, 1, 0, 0, 1, 0, 1, 0], "root": "C#", "quality": "add6", "bass": "C#"}, {"notation": "C#sus2", "array": [0, 1, 0, 1, 0, 0, 0, 0, 1, 0, 0, 0], "root": "C#", "quality": "sus2", "bass": "C#"}, {"notation": "C#sus4", "array": [0, 1, 0, 0, 0, 0, 1, 0, 1, 0, 0, 0], "root": "C#", "quality": "sus4", "bass": "C#"}, {"notation": "D", "array": [0, 0, 1, 0, 0, 0, 1, 0, 0, 1, 0, 0], "root": "D", "quality": "M", "bass": "D"}, {"notation": "Dm", "array": [0, 0, 1, 0, 0, 1, 0, 0, 0, 1, 0, 0], "root": "D", "quality": "m", "bass": "D"}, {"notation": "Daug", "array": [0, 0, 1, 0, 0, 0, 1, 0, 0, 0, 1, 0], "root": "D", "quality": "aug", "bass": "D"}, {"notation": "Ddim", "array": [0, 0, 1, 0, 0, 1, 0, 0, 1, 0, 0, 0], "root": "D", "quality": "dim", "bass": "D"}, {"notation": "D7", "array": [1, 0, 1, 0, 0, 0, 1, 0, 0, 1, 0, 0], "root": "D", "quality": "7", "bass": "D"}, {"notation": "Dm7", "array": [1, 0, 1, 0, 0, 1, 0, 0, 0, 1, 0, 0], "root": "D", "quality": "m7", "bass": "D"}, {"notation": "Dmaj7", "array": [0, 1, 1, 0, 0, 0, 1, 0, 0, 1, 0, 0], "root": "D", "quality": "maj7", "bass": "D"}, {"notation": "Ddim7", "array": [0, 0, 1, 0, 0, 1, 0, 0, 1, 0, 0, 1], "root": "D", "quality": "dim7", "bass": "D"}, {"notation": "D\u00f87", "array": [1, 0, 1, 0, 0, 1, 0, 0, 1, 0, 0, 0], "root": "D", "quality": "\u00f87", "bass": "D"}, {"notation": "D9", "array": [1, 0, 1, 0, 1, 0, 1, 0, 0, 1, 0, 0], "root": "D", "quality": "9", "bass": "D"}, {"notation": "Dadd9", "array": [0, 0, 1, 0, 1, 0, 1, 0, 0, 1, 0, 0], "root": "D", "quality": "add9", "bass": "D"}, {"notation": "Dadd6", "array": [0, 0, 1, 0, 0, 0, 1, 0, 0, 1, 0, 1], "root": "D", "quality": "add6", "bass": "D"}, {"notation": "Dsus2", "array": [0, 0, 1, 0, 1, 0, 0, 0, 0, 1, 0, 0], "root": "D", "quality": "sus2", "bass": "D"}, {"notation": "Dsus4", "array": [0, 0, 1, 0, 0, 0, 0, 1, 0, 1, 0, 0], "root": "D", "quality": "sus4", "bass": "D"}, {"notation": "D#", "array": [0, 0, 0, 1, 0, 0, 0, 1, 0, 0, 1, 0], "root": "D#", "quality": "M", "bass": "D#"}, {"notation": "D#m", "array": [0, 0, 0, 1, 0, 0, 1, 0, 0, 0, 1, 0], "root": "D#", "quality": "m", "bass": "D#"}, {"notation": "D#aug", "array": [0, 0, 0, 1, 0, 0, 0, 1, 0, 0, 0, 1], "root": "D#", "quality": "aug", "bass": "D#"}, {"notation": "D#dim", "array": [0, 0, 0, 1, 0, 0, 1, 0, 0, 1, 0, 0], "root": "D#", "quality": "dim", "bass": "D#"}, {"notation": "D#7", "array": [0, 1, 0, 1, 0, 0, 0, 1, 0, 0, 1, 0], "root": "D#", "quality": "7", "bass": "D#"}, {"notation": "D#m7", "array": [0, 1, 0, 1, 0, 0, 1, 0, 0, 0, 1, 0], "root": "D#", "quality": "m7", "bass": "D#"}, {"notation": "D#maj7", "array": [0, 0, 1, 1, 0, 0, 0, 1, 0, 0, 1, 0], "root": "D#", "quality": "maj7", "bass": "D#"}, {"notation": "D#dim7", "array": [1, 0, 0, 1, 0, 0, 1, 0, 0, 1, 0, 0], "root": "D#", "quality": "dim7", "bass": "D#"}, {"notation": "D#\u00f87", "array": [0, 1, 0, 1, 0, 0, 1, 0, 0, 1, 0, 0], "root": "D#", "quality": "\u00f87", "bass": "D#"}, {"notation": "D#9", "array": [0, 1, 0, 1, 0, 1, 0, 1, 0, 0, 1, 0], "root": "D#", "quality": "9", "bass": "D#"}, {"notation": "D#add9", "array": [0, 0, 0, 1, 0, 1, 0, 1, 0, 0, 1, 0], "root": "D#", "quality": "add9", "bass": "D#"}, {"notation": "D#add6", "array": [1, 0, 0, 1, 0, 0, 0, 1, 0, 0, 1, 0], "root": "D#", "quality": "add6", "bass": "D#"}, {"notation": "D#sus2", "array": [0, 0, 0, 1, 0, 1, 0, 0, 0, 0, 1, 0], "root": "D#", "quality": "sus2", "bass": "D#"}, {"notation": "D#sus4", "array": [0, 0, 0, 1, 0, 0, 0, 0, 1, 0, 1, 0], "root": "D#", "quality": "sus4", "bass": "D#"}, {"notation": "E", "array": [0, 0, 0, 0, 1, 0, 0, 0, 1, 0, 0, 1], "root": "E", "quality": "M", "bass": "E"}, {"notation": "Em", "array": [0, 0, 0, 0, 1, 0, 0, 1, 0, 0, 0, 1], "root": "E", "quality": "m", "bass": "E"}, {"notation": "Eaug", "array": [1, 0, 0, 0, 1, 0, 0, 0, 1, 0, 0, 0], "root": "E", "quality": "aug", "bass": "E"}, {"notation": "Edim", "array": [0, 0, 0, 0, 1, 0, 0, 1, 0, 0, 1, 0], "root": "E", "quality": "dim", "bass": "E"}, {"notation": "E7", "array": [0, 0, 1, 0, 1, 0, 0, 0, 1, 0, 0, 1], "root": "E", "quality": "7", "bass": "E"}, {"notation": "Em7", "array": [0, 0, 1, 0, 1, 0, 0, 1, 0, 0, 0, 1], "root": "E", "quality": "m7", "bass": "E"}, {"notation": "Emaj7", "array": [0, 0, 0, 1, 1, 0, 0, 0, 1, 0, 0, 1], "root": "E", "quality": "maj7", "bass": "E"}, {"notation": "Edim7", "array": [0, 1, 0, 0, 1, 0, 0, 1, 0, 0, 1, 0], "root": "E", "quality": "dim7", "bass": "E"}, {"notation": "E\u00f87", "array": [0, 0, 1, 0, 1, 0, 0, 1, 0, 0, 1, 0], "root": "E", "quality": "\u00f87", "bass": "E"}, {"notation": "E9", "array": [0, 0, 1, 0, 1, 0, 1, 0, 1, 0, 0, 1], "root": "E", "quality": "9", "bass": "E"}, {"notation": "Eadd9", "array": [0, 0, 0, 0, 1, 0, 1, 0, 1, 0, 0, 1], "root": "E", "quality": "add9", "bass": "E"}, {"notation": "Eadd6", "array": [0, 1, 0, 0, 1, 0, 0, 0, 1, 0, 0, 1], "root": "E", "quality": "add6", "bass": "E"}, {"notation": "Esus2", "array": [0, 0, 0, 0, 1, 0, 1, 0, 0, 0, 0, 1], "root": "E", "quality": "sus2", "bass": "E"}, {"notation": "Esus4", "array": [0, 0, 0, 0, 1, 0, 0, 0, 0, 1, 0, 1], "root": "E", "quality": "sus4", "bass": "E"}, {"notation": "F", "array": [1, 0, 0, 0, 0, 1, 0, 0, 0, 1, 0, 0], "root": "F", "quality": "M", "bass": "F"}, {"notation": "Fm", "array": [1, 0, 0, 0, 0, 1, 0, 0, 1, 0, 0, 0], "root": "F", "quality": "m", "bass": "F"}, {"notation": "Faug", "array": [0, 1, 0, 0, 0, 1, 0, 0, 0, 1, 0, 0], "root": "F", "quality": "aug", "bass": "F"}, {"notation": "Fdim", "array": [0, 0, 0, 0, 0, 1, 0, 0, 1, 0, 0, 1], "root": "F", "quality": "dim", "bass": "F"}, {"notation": "F7", "array": [1, 0, 0, 1, 0, 1, 0, 0, 0, 1, 0, 0], "root": "F", "quality": "7", "bass": "F"}, {"notation": "Fm7", "array": [1, 0, 0, 1, 0, 1, 0, 0, 1, 0, 0, 0], "root": "F", "quality": "m7", "bass": "F"}, {"notation": "Fmaj7", "array": [1, 0, 0, 0, 1, 1, 0, 0, 0, 1, 0, 0], "root": "F", "quality": "maj7", "bass": "F"}, {"notation": "Fdim7", "array": [0, 0, 1, 0, 0, 1, 0, 0, 1, 0, 0, 1], "root": "F", "quality": "dim7", "bass": "F"}, {"notation": "F\u00f87", "array": [0, 0, 0, 1, 0, 1, 0, 0, 1, 0, 0, 1], "root": "F", "quality": "\u00f87", "bass": "F"}, {"notation": "F9", "array": [1, 0, 0, 1, 0, 1, 0, 1, 0, 1, 0, 0], "root": "F", "quality": "9", "bass": "F"}, {"notation": "Fadd9", "array": [1, 0, 0, 0, 0, 1, 0, 1, 0, 1, 0, 0], "root": "F", "quality": "add9", "bass": "F"}, {"notation": "Fadd6", "array": [1, 0, 1, 0, 0, 1, 0, 0, 0, 1, 0, 0], "root": "F", "quality": "add6", "bass": "F"}, {"notation": "Fsus2", "array": [1, 0, 0, 0, 0, 1, 0, 1, 0, 0, 0, 0], "root": "F", "quality": "sus2", "bass": "F"}, {"notation": "Fsus4", "array": [1, 0, 0, 0, 0, 1, 0, 0, 0, 0, 1, 0], "root": "F", "quality": "sus4", "bass": "F"}, {"notation": "F#", "array": [0, 1, 0, 0, 0, 0, 1, 0, 0, 0, 1, 0], "root": "F#", "quality": "M", "bass": "F#"}, {"notation": "F#m", "array": [0, 1, 0, 0, 0, 0, 1, 0, 0, 1, 0, 0], "root": "F#", "quality": "m", "bass": "F#"}, {"notation": "F#aug", "array": [0, 0, 1, 0, 0, 0, 1, 0, 0, 0, 1, 0], "root": "F#", "quality": "aug", "bass": "F#"}, {"notation": "F#dim", "array": [1, 0, 0, 0, 0, 0, 1, 0, 0, 1, 0, 0], "root": "F#", "quality": "dim", "bass": "F#"}, {"notation": "F#7", "array": [0, 1, 0, 0, 1, 0, 1, 0, 0, 0, 1, 0], "root": "F#", "quality": "7", "bass": "F#"}, {"notation": "F#m7", "array": [0, 1, 0, 0, 1, 0, 1, 0, 0, 1, 0, 0], "root": "F#", "quality": "m7", "bass": "F#"}, {"notation": "F#maj7", "array": [0, 1, 0, 0, 0, 1, 1, 0, 0, 0, 1, 0], "root": "F#", "quality": "maj7", "bass": "F#"}, {"notation": "F#dim7", "array": [1, 0, 0, 1, 0, 0, 1, 0, 0, 1, 0, 0], "root": "F#", "quality": "dim7", "bass": "F#"}, {"notation": "F#\u00f87", "array": [1, 0, 0, 0, 1, 0, 1, 0, 0, 1, 0, 0], "root": "F#", "quality": "\u00f87", "bass": "F#"}, {"notation": "F#9", "array": [0, 1, 0, 0, 1, 0, 1, 0, 1, 0, 1, 0], "root": "F#", "quality": "9", "bass": "F#"}, {"notation": "F#add9", "array": [0, 1, 0, 0, 0, 0, 1, 0, 1, 0, 1, 0], "root": "F#", "quality": "add9", "bass": "F#"}, {"notation": "F#add6", "array": [0, 1, 0, 1, 0, 0, 1, 0, 0, 0, 1, 0], "root": "F#", "quality": "add6", "bass": "F#"}, {"notation": "F#sus2", "array": [0, 1, 0, 0, 0, 0, 1, 0, 1, 0, 0, 0], "root": "F#", "quality": "sus2", "bass": "F#"}, {"notation": "F#sus4", "array": [0, 1, 0, 0, 0, 0, 1, 0, 0, 0, 0, 1], "root": "F#", "quality": "sus4", "bass": "F#"}, {"notation": "G", "array": [0, 0, 1, 0, 0, 0, 0, 1, 0, 0, 0, 1], "root": "G", "quality": "M", "bass": "G"}, {"notation": "Gm", "array": [0, 0, 1, 0, 0, 0, 0, 1, 0, 0, 1, 0], "root": "G", "quality": "m", "bass": "G"}, {"notation": "Gaug", "array": [0, 0, 0, 1, 0, 0, 0, 1, 0, 0, 0, 1], "root": "G", "quality": "aug", "bass": "G"}, {"notation": "Gdim", "array": [0, 1, 0, 0, 0, 0, 0, 1, 0, 0, 1, 0], "root": "G", "quality": "dim", "bass": "G"}, {"notation": "G7", "array": [0, 0, 1, 0, 0, 1, 0, 1, 0, 0, 0, 1], "root": "G", "quality": "7", "bass": "G"}, {"notation": "Gm7", "array": [0, 0, 1, 0, 0, 1, 0, 1, 0, 0, 1, 0], "root": "G", "quality": "m7", "bass": "G"}, {"notation": "Gmaj7", "array": [0, 0, 1, 0, 0, 0, 1, 1, 0, 0, 0, 1], "root": "G", "quality": "maj7", "bass": "G"}, {"notation": "Gdim7", "array": [0, 1, 0, 0, 1, 0, 0, 1, 0, 0, 1, 0], "root": "G", "quality": "dim7", "bass": "G"}, {"notation": "G\u00f87", "array": [0, 1, 0, 0, 0, 1, 0, 1, 0, 0, 1, 0], "root": "G", "quality": "\u00f87", "bass": "G"}, {"notation": "G9", "array": [0, 0, 1, 0, 0, 1, 0, 1, 0, 1, 0, 1], "root": "G", "quality": "9", "bass": "G"}, {"notation": "Gadd9", "array": [0, 0, 1, 0, 0, 0, 0, 1, 0, 1, 0, 1], "root": "G", "quality": "add9", "bass": "G"}, {"notation": "Gadd6", "array": [0, 0, 1, 0, 1, 0, 0, 1, 0, 0, 0, 1], "root": "G", "quality": "add6", "bass": "G"}, {"notation": "Gsus2", "array": [0, 0, 1, 0, 0, 0, 0, 1, 0, 1, 0, 0], "root": "G", "quality": "sus2", "bass": "G"}, {"notation": "Gsus4", "array": [1, 0, 1, 0, 0, 0, 0, 1, 0, 0, 0, 0], "root": "G", "quality": "sus4", "bass": "G"}, {"notation": "G#", "array": [1, 0, 0, 1, 0, 0, 0, 0, 1, 0, 0, 0], "root": "G#", "quality": "M", "bass": "G#"}, {"notation": "G#m", "array": [0, 0, 0, 1, 0, 0, 0, 0, 1, 0, 0, 1], "root": "G#", "quality": "m", "bass": "G#"}, {"notation": "G#aug", "array": [1, 0, 0, 0, 1, 0, 0, 0, 1, 0, 0, 0], "root": "G#", "quality": "aug", "bass": "G#"}, {"notation": "G#dim", "array": [0, 0, 1, 0, 0, 0, 0, 0, 1, 0, 0, 1], "root": "G#", "quality": "dim", "bass": "G#"}, {"notation": "G#7", "array": [1, 0, 0, 1, 0, 0, 1, 0, 1, 0, 0, 0], "root": "G#", "quality": "7", "bass": "G#"}, {"notation": "G#m7", "array": [0, 0, 0, 1, 0, 0, 1, 0, 1, 0, 0, 1], "root": "G#", "quality": "m7", "bass": "G#"}, {"notation": "G#maj7", "array": [1, 0, 0, 1, 0, 0, 0, 1, 1, 0, 0, 0], "root": "G#", "quality": "maj7", "bass": "G#"}, {"notation": "G#dim7", "array": [0, 0, 1, 0, 0, 1, 0, 0, 1, 0, 0, 1], "root": "G#", "quality": "dim7", "bass": "G#"}, {"notation": "G#\u00f87", "array": [0, 0, 1, 0, 0, 0, 1, 0, 1, 0, 0, 1], "root": "G#", "quality": "\u00f87", "bass": "G#"}, {"notation": "G#9", "array": [1, 0, 0, 1, 0, 0, 1, 0, 1, 0, 1, 0], "root": "G#", "quality": "9", "bass": "G#"}, {"notation": "G#add9", "array": [1, 0, 0, 1, 0, 0, 0, 0, 1, 0, 1, 0], "root": "G#", "quality": "add9", "bass": "G#"}, {"notation": "G#add6", "array": [1, 0, 0, 1, 0, 1, 0, 0, 1, 0, 0, 0], "root": "G#", "quality": "add6", "bass": "G#"}, {"notation": "G#sus2", "array": [0, 0, 0, 1, 0, 0, 0, 0, 1, 0, 1, 0], "root": "G#", "quality": "sus2", "bass": "G#"}, {"notation": "G#sus4", "array": [0, 1, 0, 1, 0, 0, 0, 0, 1, 0, 0, 0], "root": "G#", "quality": "sus4", "bass": "G#"}, {"notation": "A", "array": [0, 1, 0, 0, 1, 0, 0, 0, 0, 1, 0, 0], "root": "A", "quality": "M", "bass": "A"}, {"notation": "Am", "array": [1, 0, 0, 0, 1, 0, 0, 0, 0, 1, 0, 0], "root": "A", "quality": "m", "bass": "A"}, {"notation": "Aaug", "array": [0, 1, 0, 0, 0, 1, 0, 0, 0, 1, 0, 0], "root": "A", "quality": "aug", "bass": "A"}, {"notation": "Adim", "array": [1, 0, 0, 1, 0, 0, 0, 0, 0, 1, 0, 0], "root": "A", "quality": "dim", "bass": "A"}, {"notation": "A7", "array": [0, 1, 0, 0, 1, 0, 0, 1, 0, 1, 0, 0], "root": "A", "quality": "7", "bass": "A"}, {"notation": "Am7", "array": [1, 0, 0, 0, 1, 0, 0, 1, 0, 1, 0, 0], "root": "A", "quality": "m7", "bass": "A"}, {"notation": "Amaj7", "array": [0, 1, 0, 0, 1, 0, 0, 0, 1, 1, 0, 0], "root": "A", "quality": "maj7", "bass": "A"}, {"notation": "Adim7", "array": [1, 0, 0, 1, 0, 0, 1, 0, 0, 1, 0, 0], "root": "A", "quality": "dim7", "bass": "A"}, {"notation": "A\u00f87", "array": [1, 0, 0, 1, 0, 0, 0, 1, 0, 1, 0, 0], "root": "A", "quality": "\u00f87", "bass": "A"}, {"notation": "A9", "array": [0, 1, 0, 0, 1, 0, 0, 1, 0, 1, 0, 1], "root": "A", "quality": "9", "bass": "A"}, {"notation": "Aadd9", "array": [0, 1, 0, 0, 1, 0, 0, 0, 0, 1, 0, 1], "root": "A", "quality": "add9", "bass": "A"}, {"notation": "Aadd6", "array": [0, 1, 0, 0, 1, 0, 1, 0, 0, 1, 0, 0], "root": "A", "quality": "add6", "bass": "A"}, {"notation": "Asus2", "array": [0, 0, 0, 0, 1, 0, 0, 0, 0, 1, 0, 1], "root": "A", "quality": "sus2", "bass": "A"}, {"notation": "Asus4", "array": [0, 0, 1, 0, 1, 0, 0, 0, 0, 1, 0, 0], "root": "A", "quality": "sus4", "bass": "A"}, {"notation": "A#", "array": [0, 0, 1, 0, 0, 1, 0, 0, 0, 0, 1, 0], "root": "A#", "quality": "M", "bass": "A#"}, {"notation": "A#m", "array": [0, 1, 0, 0, 0, 1, 0, 0, 0, 0, 1, 0], "root": "A#", "quality": "m", "bass": "A#"}, {"notation": "A#aug", "array": [0, 0, 1, 0, 0, 0, 1, 0, 0, 0, 1, 0], "root": "A#", "quality": "aug", "bass": "A#"}, {"notation": "A#dim", "array": [0, 1, 0, 0, 1, 0, 0, 0, 0, 0, 1, 0], "root": "A#", "quality": "dim", "bass": "A#"}, {"notation": "A#7", "array": [0, 0, 1, 0, 0, 1, 0, 0, 1, 0, 1, 0], "root": "A#", "quality": "7", "bass": "A#"}, {"notation": "A#m7", "array": [0, 1, 0, 0, 0, 1, 0, 0, 1, 0, 1, 0], "root": "A#", "quality": "m7", "bass": "A#"}, {"notation": "A#maj7", "array": [0, 0, 1, 0, 0, 1, 0, 0, 0, 1, 1, 0], "root": "A#", "quality": "maj7", "bass": "A#"}, {"notation": "A#dim7", "array": [0, 1, 0, 0, 1, 0, 0, 1, 0, 0, 1, 0], "root": "A#", "quality": "dim7", "bass": "A#"}, {"notation": "A#\u00f87", "array": [0, 1, 0, 0, 1, 0, 0, 0, 1, 0, 1, 0], "root": "A#", "quality": "\u00f87", "bass": "A#"}, {"notation": "A#9", "array": [1, 0, 1, 0, 0, 1, 0, 0, 1, 0, 1, 0], "root": "A#", "quality": "9", "bass": "A#"}, {"notation": "A#add9", "array": [1, 0, 1, 0, 0, 1, 0, 0, 0, 0, 1, 0], "root": "A#", "quality": "add9", "bass": "A#"}, {"notation": "A#add6", "array": [0, 0, 1, 0, 0, 1, 0, 1, 0, 0, 1, 0], "root": "A#", "quality": "add6", "bass": "A#"}, {"notation": "A#sus2", "array": [1, 0, 0, 0, 0, 1, 0, 0, 0, 0, 1, 0], "root": "A#", "quality": "sus2", "bass": "A#"}, {"notation": "A#sus4", "array": [0, 0, 0, 1, 0, 1, 0, 0, 0, 0, 1, 0], "root": "A#", "quality": "sus4", "bass": "A#"}, {"notation": "B", "array": [0, 0, 0, 1, 0, 0, 1, 0, 0, 0, 0, 1], "root": "B", "quality": "M", "bass": "B"}, {"notation": "Bm", "array": [0, 0, 1, 0, 0, 0, 1, 0, 0, 0, 0, 1], "root": "B", "quality": "m", "bass": "B"}, {"notation": "Baug", "array": [0, 0, 0, 1, 0, 0, 0, 1, 0, 0, 0, 1], "root": "B", "quality": "aug", "bass": "B"}, {"notation": "Bdim", "array": [0, 0, 1, 0, 0, 1, 0, 0, 0, 0, 0, 1], "root": "B", "quality": "dim", "bass": "B"}, {"notation": "B7", "array": [0, 0, 0, 1, 0, 0, 1, 0, 0, 1, 0, 1], "root": "B", "quality": "7", "bass": "B"}, {"notation": "Bm7", "array": [0, 0, 1, 0, 0, 0, 1, 0, 0, 1, 0, 1], "root": "B", "quality": "m7", "bass": "B"}, {"notation": "Bmaj7", "array": [0, 0, 0, 1, 0, 0, 1, 0, 0, 0, 1, 1], "root": "B", "quality": "maj7", "bass": "B"}, {"notation": "Bdim7", "array": [0, 0, 1, 0, 0, 1, 0, 0, 1, 0, 0, 1], "root": "B", "quality": "dim7", "bass": "B"}, {"notation": "B\u00f87", "array": [0, 0, 1, 0, 0, 1, 0, 0, 0, 1, 0, 1], "root": "B", "quality": "\u00f87", "bass": "B"}, {"notation": "B9", "array": [0, 1, 0, 1, 0, 0, 1, 0, 0, 1, 0, 1], "root": "B", "quality": "9", "bass": "B"}, {"notation": "Badd9", "array": [0, 1, 0, 1, 0, 0, 1, 0, 0, 0, 0, 1], "root": "B", "quality": "add9", "bass": "B"}, {"notation": "Badd6", "array": [0, 0, 0, 1, 0, 0, 1, 0, 1, 0, 0, 1], "root": "B", "quality": "add6", "bass": "B"}, {"notation": "Bsus2", "array": [0, 1, 0, 0, 0, 0, 1, 0, 0, 0, 0, 1], "root": "B", "quality": "sus2", "bass": "B"}, {"notation": "Bsus4", "array": [0, 0, 0, 0, 1, 0, 1, 0, 0, 0, 0, 1], "root": "B", "quality": "sus4", "bass": "B"}]}